<?xml version='1.0' encoding='UTF-8' ?>

<!-- 
This is the JBoss EJB deployment descriptor for the Query EJB.
-->

<jboss>

  <enterprise-beans>

    <session>
      <ejb-name>Query</ejb-name>
      <jndi-name>QueryHome</jndi-name>
      <resource-ref>
        <res-ref-name>jdbc/rubis</res-ref-name>
        <resource-name>rubis</resource-name>
      </resource-ref>
    </session>

  </enterprise-beans>


  <resource-managers>

    <resource-manager>
      <res-name>rubis</res-name>
      <res-jndi-name>java:/rubis_entitybean_BMP</res-jndi-name>
    </resource-manager>

  </resource-managers>

</jboss>

