<jboss>
  <enterprise-beans>
    <entity>
      <ejb-name>TheAccount</ejb-name>
      <resource-ref>
        <res-ref-name>jdbc/EstoreDataSource</res-ref-name>
        <resource-name>EstoreDB</resource-name>
      </resource-ref>
    </entity>

    <entity>
      <ejb-name>TheOrder</ejb-name>
      <resource-ref>
        <res-ref-name>jdbc/EstoreDataSource</res-ref-name>
        <resource-name>EstoreDB</resource-name>
      </resource-ref>
    </entity>
  </enterprise-beans>

  <resource-managers>
    <resource-manager res-class="javax.sql.DataSource">
      <res-name>EstoreDB</res-name>
      <res-jndi-name>java:/EstoreDB</res-jndi-name>
    </resource-manager>
  </resource-managers>
</jboss>
